README.md
VERSION
fling/__init__.py
fling/middleware.py
fling/start.py
fling/static/start/styles.css
fling/templates/admin/index.html
fling/templates/start/base.html
fling/templates/start/index.html
fling/templates/start/x3d.html
fling_start-0.1.14.dist-info/METADATA
fling_start-0.1.14.dist-info/WHEEL
fling_start-0.1.14.dist-info/RECORD
