Metadata-Version: 2.1
Name: fling-start
Version: 0.1.14
Summary: Side Project Management from the command line
Author: Joshua McKenty
Author-email: jmckenty@gmail.com
Requires-Python: >=3.9,<4.0
Classifier: Programming Language :: Python :: 3
Classifier: Programming Language :: Python :: 3.9
Classifier: Programming Language :: Python :: 3.10
Classifier: Programming Language :: Python :: 3.11
Requires-Dist: bootstrap-flask (>=2.2.0,<3.0.0)
Requires-Dist: flask
Requires-Dist: flask-admin (>=1.6.1,<2.0.0)
Requires-Dist: flask-babel (>=3.1.0,<4.0.0)
Requires-Dist: flask-caching (>=2.0.2,<3.0.0)
Requires-Dist: flask-rich (>=0.3.0,<0.4.0)
Requires-Dist: python-dotenv
Project-URL: documentation, https://readthedocs.org/fling-start
Project-URL: homepage, https://fling.wtf
Project-URL: repository, https://github.com/10in30/fling-start.git
